servir/__init__.py
servir/_background_server.py
servir/_protocols.py
servir/_provide.py
servir/_resources.py
servir/_tilesets.py
servir/_util.py
servir/py.typed
servir-0.2.1.dist-info/METADATA
servir-0.2.1.dist-info/WHEEL
servir-0.2.1.dist-info/licenses/LICENSE
servir-0.2.1.dist-info/RECORD
