Metadata-Version: 2.3
Name: servir
Version: 0.2.1
Summary: an extensible async background server
Project-URL: Documentation, https://github.com/unknown/servir#readme
Project-URL: Issues, https://github.com/unknown/servir/issues
Project-URL: Source, https://github.com/unknown/servir
Author-email: Trevor Manz <trevor.j.manz@gmail.com>
License: MIT
License-File: LICENSE
Classifier: Development Status :: 4 - Beta
Classifier: Programming Language :: Python
Classifier: Programming Language :: Python :: 3.8
Classifier: Programming Language :: Python :: 3.9
Classifier: Programming Language :: Python :: 3.10
Classifier: Programming Language :: Python :: 3.11
Classifier: Programming Language :: Python :: Implementation :: CPython
Classifier: Programming Language :: Python :: Implementation :: PyPy
Requires-Python: >=3.8
Requires-Dist: portpicker
Requires-Dist: starlette>=0.35
Requires-Dist: typing-extensions>=4.5.0; python_version < '3.11'
Requires-Dist: uvicorn>=0.21.1
Provides-Extra: dev
Requires-Dist: coverage[toml]>=6.5; extra == 'dev'
Requires-Dist: mypy>=1.0.0; extra == 'dev'
Requires-Dist: pytest; extra == 'dev'
Requires-Dist: requests; extra == 'dev'
Requires-Dist: ruff; extra == 'dev'
